app/__init__.py
app/cli.py
app/main.py
app/mcp/__init__.py
app/models/__init__.py
app/models/config.py
app/models/embedding_models.py
app/models/memory.py
app/search/__init__.py
app/search/embeddings.py
app/search/model_downloader.py
app/services/__init__.py
app/services/memory_cleanup.py
app/storage/__init__.py
app/storage/vector_store.py
app/tui/__init__.py
app/tui/app.py
app/tui/memory_manager.py
app/tui/themes.py
app/tui/screens/__init__.py
app/tui/screens/main_menu.py
app/tui/screens/memory_management.py
app/tui/screens/modals/__init__.py
app/tui/screens/modals/add_memory.py
app/tui/screens/modals/edit_memory.py
app/tui/screens/modals/embedding_model_select.py
app/tui/screens/modals/setup_result.py
app/tui/screens/modals/storage_config.py
app/tui/screens/modals/theme_select.py
app/tui/settings/__init__.py
app/tui/settings/settings_screen.py
app/tui/settings/setup_screen.py
app/tui/styles/app.tcss
app/tui/styles/modal.tcss
app/tui/styles/screens.tcss
app/tui/styles/settings.tcss
app/tui/utils/__init__.py
app/tui/utils/config_manager.py
app/tui/utils/setup_runner.py
app/tui/widgets/__init__.py
app/tui/widgets/collapsible_item.py
yaade-0.1.0.dist-info/METADATA
yaade-0.1.0.dist-info/WHEEL
yaade-0.1.0.dist-info/entry_points.txt
yaade-0.1.0.dist-info/licenses/LICENSE
yaade-0.1.0.dist-info/RECORD
