Metadata-Version: 2.4
Name: yaade
Version: 0.1.0
Summary: Yaade (यादें) - Local MCP-compatible memory storage for AI agents with semantic search
Project-URL: Homepage, https://github.com/reyanshgupta/yaade
Project-URL: Repository, https://github.com/reyanshgupta/yaade
Project-URL: Issues, https://github.com/reyanshgupta/yaade/issues
Project-URL: Documentation, https://github.com/reyanshgupta/yaade#readme
Author: Reyansh Gupta
License: MIT
License-File: LICENSE
Keywords: ai,claude,embeddings,mcp,memory,vector-database
Classifier: Intended Audience :: Developers
Classifier: License :: OSI Approved :: MIT License
Classifier: Programming Language :: Python :: 3
Classifier: Programming Language :: Python :: 3.12
Classifier: Topic :: Scientific/Engineering :: Artificial Intelligence
Classifier: Topic :: Software Development :: Libraries :: Python Modules
Requires-Python: >=3.12
Requires-Dist: build>=1.3.0
Requires-Dist: chromadb>=1.0.15
Requires-Dist: fastapi[standard]>=0.116.1
Requires-Dist: mcp-server>=0.1.4
Requires-Dist: mcp[cli]>=1.12.3
Requires-Dist: numpy>=1.24.0
Requires-Dist: pydantic-settings>=2.5.2
Requires-Dist: rich>=13.0.0
Requires-Dist: sentence-transformers>=5.0.0
Requires-Dist: textual>=0.70.0
Requires-Dist: twine>=6.2.0
Provides-Extra: dev
Requires-Dist: pytest-asyncio>=0.23.0; extra == 'dev'
Requires-Dist: pytest-cov>=4.1.0; extra == 'dev'
Requires-Dist: pytest-mock>=3.12.0; extra == 'dev'
Requires-Dist: pytest>=8.0.0; extra == 'dev'
